INSTALL
MANIFEST.in
README.rst
setup.cfg
setup.py
./__init__.py
./party.py
./party.xml
./tryton.cfg
./tests/__init__.py
./tests/test_party.py
trytonacs_party_access_control_isonas.egg-info/PKG-INFO
trytonacs_party_access_control_isonas.egg-info/SOURCES.txt
trytonacs_party_access_control_isonas.egg-info/dependency_links.txt
trytonacs_party_access_control_isonas.egg-info/entry_points.txt
trytonacs_party_access_control_isonas.egg-info/not-zip-safe
trytonacs_party_access_control_isonas.egg-info/requires.txt
trytonacs_party_access_control_isonas.egg-info/top_level.txt