Metadata-Version: 1.1
Name: trytonacs-party-access-control-isonas
Version: 3.4.2
Summary: Tryton integration with ISONAS Access Controller software     Crystal Matrix
Home-page: http://www.lavalab.com.au/
Author: Lava Lab Software Pty Ltd
Author-email: mail@lavalab.com.au
License: GPL-3
Platform: UNKNOWN
Classifier: Development Status :: 4 - Beta
Classifier: Environment :: Plugins
Classifier: Intended Audience :: Developers
Classifier: License :: OSI Approved :: GNU General Public License v3 (GPLv3)
Classifier: Natural Language :: English
Classifier: Operating System :: OS Independent
Classifier: Programming Language :: Python
Classifier: Framework :: Tryton
Classifier: Topic :: Office/Business
